cheomseongdae/__init__.py
cheomseongdae/cheomseongdae.py
cheomseongdae-0.1.2.dist-info/LICENSE
cheomseongdae-0.1.2.dist-info/METADATA
cheomseongdae-0.1.2.dist-info/WHEEL
cheomseongdae-0.1.2.dist-info/entry_points.txt
cheomseongdae-0.1.2.dist-info/top_level.txt
cheomseongdae-0.1.2.dist-info/RECORD
